<?xml version="1.0" encoding="UTF-8"?>
<song>
  <title>Con aceite (#203 Nuevo Himnario Adventista)</title>
  <author></author>
  <copyright></copyright>
  <hymn_number></hymn_number>
  <presentation></presentation>
  <ccli></ccli>
  <capo print="false"></capo>
  <key>D</key>
  <aka></aka>
  <key_line></key_line>
  <user1></user1>
  <user2></user2>
  <user3></user3>
  <theme></theme>
  <tempo></tempo>
  <time_sig></time_sig>
  <lyrics>.Tono: Re  Ritmo: 4/4
[V1]
.     D.               G.          D.        E.     A.
 Con aceite mi lámpara brilla y su luz me inspira valor,
.     D.               G.            D.           A.       D.
 con aceite mi lámpara brilla, Brillará hasta que venga el Rey.
[C]
.D.           G.           A.                 D.
 Cantaré, si, cantaré, si, cantaré a Jesús el Rey, el Rey,
.D.           G.           A.                 D.
 Cantaré, si, cantaré, si, cantaré a Jesús el Rey, el Rey.
 </lyrics></song>